<?xml version="1.0" encoding="utf-8"?><index><!-- saved from url=(0016)http://localhost -->
<stem n="enough"><phr n="enough"><ent r="3" t="54" w="127" /></phr></stem><stem n="proce"><phr n="proceed"><ent r="3" t="54" w="130" /></phr></stem><stem n="disallow"><phr n="disallows"><ent r="3" t="54" w="173" /><ent r="3" t="54" w="196" /></phr></stem><stem n="expir"><phr n="expires"><ent r="4" t="54" w="185" /></phr><phr n="Expiration"><ent r="4" t="257" w="60" /></phr></stem><stem n="disabl"><phr n="disables"><ent r="3" t="54" w="189" /><ent r="3" t="81" w="114" /><ent r="3" t="82" w="118" /><ent r="3" t="244" w="507" /><ent r="3" t="245" w="1120" /><ent r="3" t="282" w="803" /></phr><phr n="Disabilities"><ent r="7" t="64" w="557" /><ent r="7" t="64" w="572" /></phr><phr n="disability"><ent r="7" t="64" w="1480" /><ent r="7" t="64" w="1680" /></phr><phr n="disable"><ent r="4" t="70" w="160" /><ent r="4" t="71" w="85" /><ent r="102" t="80" w="6" /><ent r="100" t="80" w="13" /><ent r="3" t="80" w="17" /><ent r="3" t="80" w="32" /><ent r="3" t="80" w="80" /><ent r="5" t="80" w="116" /><ent r="102" t="81" w="7" /><ent r="3" t="81" w="15" /><ent r="3" t="81" w="29" /><ent r="3" t="81" w="86" /><ent r="4" t="81" w="105" /><ent r="102" t="82" w="8" /><ent r="3" t="82" w="17" /><ent r="3" t="82" w="31" /><ent r="3" t="82" w="88" /><ent r="4" t="82" w="109" /><ent r="102" t="105" w="4" /><ent r="100" t="105" w="9" /><ent r="100" t="105" w="13" /><ent r="100" t="105" w="17" /><ent r="3" t="105" w="38" /><ent r="3" t="105" w="60" /><ent r="3" t="105" w="122" /><ent r="4" t="105" w="144" /><ent r="5" t="105" w="149" /><ent r="3" t="163" w="355" /><ent r="3" t="163" w="565" /><ent r="3" t="239" w="244" /><ent r="6" t="243" w="899" /><ent r="3" t="244" w="528" /><ent r="3" t="244" w="534" /><ent r="3" t="244" w="544" /><ent r="3" t="244" w="590" /><ent r="6" t="245" w="514" /><ent r="3" t="245" w="1203" /><ent r="3" t="245" w="1209" /><ent r="3" t="245" w="1219" /><ent r="3" t="279" w="289" /><ent r="3" t="282" w="253" /><ent r="3" t="282" w="259" /><ent r="3" t="282" w="269" /><ent r="65" t="307" w="223" /></phr><phr n="disabled"><ent r="4" t="77" w="103" /><ent r="3" t="163" w="437" /><ent r="3" t="184" w="161" /><ent r="3" t="239" w="310" /><ent r="3" t="243" w="528" /><ent r="3" t="243" w="569" /><ent r="4" t="282" w="132" /><ent r="3" t="282" w="971" /></phr><phr n="Disabling"><ent r="1000" t="80" w="1" /><ent r="1000" t="81" w="1" /><ent r="1000" t="82" w="1" /><ent r="1000" t="105" w="1" /><ent r="3" t="105" w="19" /><ent r="3" t="105" w="52" /><ent r="4" t="117" w="90" /><ent r="3" t="244" w="582" /></phr></stem><stem n="-collect"><phr n="-collected"><ent r="3" t="54" w="211" /><ent r="3" t="54" w="211" /></phr></stem><stem n="previously-collect"><phr n="previously-collected"><ent r="3" t="54" w="211" /></phr></stem><stem n="circumst"><phr n="circumstances"><ent r="3" t="55" w="28" /><ent r="3" t="83" w="220" /></phr></stem><stem n="exhaust"><phr n="exhaust"><ent r="4" t="55" w="37" /><ent r="4" t="55" w="58" /></phr></stem><stem n="remain"><phr n="remain"><ent r="4" t="55" w="76" /><ent r="7" t="64" w="439" /><ent r="3" t="81" w="68" /><ent r="3" t="82" w="70" /><ent r="3" t="83" w="367" /><ent r="3" t="86" w="151" /><ent r="3" t="142" w="54" /><ent r="3" t="163" w="388" /><ent r="3" t="163" w="536" /><ent r="3" t="279" w="233" /></phr><phr n="remains"><ent r="3" t="57" w="34" /><ent r="3" t="136" w="51" /><ent r="3" t="137" w="284" /><ent r="4" t="149" w="105" /><ent r="4" t="152" w="87" /><ent r="3" t="163" w="280" /><ent r="3" t="239" w="179" /><ent r="3" t="239" w="278" /><ent r="3" t="239" w="412" /><ent r="4" t="311" w="69" /></phr><phr n="remaining"><ent r="3" t="73" w="81" /><ent r="3" t="317" w="101" /></phr></stem><stem n="bar"><phr n="bar"><ent r="4" t="55" w="92" /><ent r="4" t="66" w="48" /><ent r="4" t="67" w="60" /><ent r="4" t="140" w="143" /><ent r="4" t="140" w="164" /><ent r="4" t="142" w="203" /><ent r="4" t="144" w="92" /><ent r="4" t="146" w="96" /><ent r="4" t="151" w="177" /></phr></stem><stem n=":enabl"><phr n=":enable"><ent r="100" t="56" w="20" /><ent r="100" t="56" w="35" /><ent r="100" t="70" w="14" /><ent r="100" t="70" w="19" /><ent r="100" t="71" w="20" /><ent r="100" t="79" w="13" /><ent r="100" t="106" w="12" /><ent r="100" t="106" w="16" /><ent r="100" t="106" w="20" /></phr></stem><stem n=":regist"><phr n=":register"><ent r="100" t="56" w="30" /></phr></stem><stem n=":appli"><phr n=":apply"><ent r="100" t="56" w="39" /><ent r="100" t="56" w="44" /><ent r="100" t="70" w="23" /><ent r="100" t="70" w="28" /><ent r="100" t="70" w="33" /><ent r="100" t="70" w="38" /></phr></stem><stem n="sox"><phr n="SOX"><ent r="100" t="56" w="40" /><ent r="3" t="56" w="1037" /><ent r="7" t="56" w="1044" /><ent r="8" t="56" w="1054" /><ent r="7" t="56" w="1082" /><ent r="5" t="56" w="1132" /><ent r="100" t="64" w="19" /><ent r="92" t="64" w="2172" /><ent r="100" t="70" w="29" /><ent r="3" t="70" w="1053" /><ent r="7" t="70" w="1060" /><ent r="8" t="70" w="1070" /><ent r="7" t="70" w="1098" /><ent r="5" t="70" w="1149" /></phr></stem><stem n="ferpa"><phr n="FERPA"><ent r="100" t="56" w="45" /><ent r="3" t="56" w="929" /><ent r="7" t="56" w="936" /><ent r="8" t="56" w="946" /><ent r="7" t="56" w="973" /><ent r="5" t="56" w="1023" /><ent r="100" t="64" w="16" /><ent r="92" t="64" w="217" /><ent r="7" t="64" w="343" /><ent r="7" t="64" w="602" /><ent r="100" t="70" w="24" /><ent r="3" t="70" w="933" /><ent r="7" t="70" w="940" /><ent r="8" t="70" w="950" /><ent r="7" t="70" w="978" /><ent r="5" t="70" w="1029" /></phr></stem><stem n="correspond"><phr n="corresponding"><ent r="3" t="56" w="72" /><ent r="92" t="60" w="62" /><ent r="3" t="64" w="57" /><ent r="4" t="88" w="292" /><ent r="3" t="93" w="160" /><ent r="3" t="94" w="219" /><ent r="3" t="102" w="221" /><ent r="3" t="105" w="54" /><ent r="3" t="106" w="34" /><ent r="3" t="113" w="34" /><ent r="3" t="118" w="55" /><ent r="3" t="125" w="641" /><ent r="3" t="126" w="49" /><ent r="3" t="139" w="88" /><ent r="3" t="142" w="83" /><ent r="3" t="143" w="44" /><ent r="4" t="149" w="184" /><ent r="4" t="152" w="194" /><ent r="3" t="168" w="677" /><ent r="3" t="169" w="85" /><ent r="3" t="170" w="922" /><ent r="3" t="173" w="77" /><ent r="3" t="174" w="179" /><ent r="3" t="188" w="80" /><ent r="3" t="199" w="75" /><ent r="3" t="213" w="311" /><ent r="3" t="220" w="39" /><ent r="3" t="222" w="284" /><ent r="3" t="223" w="95" /><ent r="3" t="224" w="192" /><ent r="3" t="225" w="322" /><ent r="3" t="226" w="160" /><ent r="3" t="227" w="282" /><ent r="3" t="228" w="199" /><ent r="3" t="229" w="204" /><ent r="3" t="230" w="335" /><ent r="3" t="231" w="159" /><ent r="3" t="232" w="348" /><ent r="3" t="233" w="171" /><ent r="3" t="234" w="150" /><ent r="3" t="235" w="285" /><ent r="3" t="236" w="203" /><ent r="3" t="237" w="147" /><ent r="3" t="238" w="286" /><ent r="4" t="242" w="80" /><ent r="3" t="243" w="626" /><ent r="6" t="243" w="891" /><ent r="3" t="244" w="560" /><ent r="3" t="245" w="236" /><ent r="6" t="245" w="506" /><ent r="3" t="245" w="1232" /><ent r="3" t="249" w="35" /><ent r="3" t="255" w="94" /><ent r="3" t="258" w="282" /><ent r="3" t="259" w="89" /><ent r="3" t="260" w="240" /><ent r="3" t="261" w="396" /><ent r="3" t="262" w="162" /><ent r="3" t="263" w="284" /><ent r="3" t="264" w="244" /><ent r="3" t="265" w="199" /><ent r="3" t="266" w="334" /><ent r="3" t="267" w="206" /><ent r="3" t="268" w="172" /><ent r="3" t="269" w="151" /><ent r="3" t="270" w="347" /><ent r="3" t="274" w="285" /><ent r="3" t="275" w="245" /><ent r="3" t="276" w="145" /><ent r="3" t="278" w="77" /><ent r="3" t="282" w="282" /><ent r="3" t="294" w="253" /><ent r="3" t="304" w="155" /><ent r="4" t="311" w="174" /><ent r="3" t="323" w="43" /></phr><phr n="corresponds"><ent r="3" t="170" w="322" /></phr></stem><stem n="checkbox"><phr n="checkbox"><ent r="4" t="56" w="214" /><ent r="3" t="200" w="100" /><ent r="3" t="254" w="158" /></phr></stem><stem n="\idera\sqlcompliance\agenttracefil"><phr n="\Idera\SQLcompliance\AgentTraceFiles"><ent r="4" t="56" w="392" /><ent r="4" t="203" w="62" /><ent r="4" t="216" w="49" /></phr></stem><stem n="transact"><phr n="transaction"><ent r="4" t="56" w="618" /><ent r="7" t="57" w="817" /><ent r="7" t="61" w="852" /><ent r="4" t="149" w="51" /><ent r="4" t="149" w="158" /><ent r="4" t="149" w="175" /><ent r="4" t="151" w="118" /><ent r="4" t="152" w="44" /><ent r="4" t="152" w="162" /><ent r="4" t="152" w="185" /><ent r="3" t="173" w="330" /><ent r="3" t="173" w="428" /><ent r="3" t="174" w="327" /><ent r="3" t="174" w="355" /><ent r="3" t="174" w="373" /><ent r="3" t="174" w="454" /><ent r="3" t="188" w="333" /><ent r="3" t="188" w="431" /><ent r="3" t="196" w="329" /><ent r="3" t="196" w="427" /><ent r="3" t="208" w="82" /><ent r="3" t="208" w="100" /><ent r="3" t="208" w="114" /><ent r="3" t="209" w="61" /><ent r="3" t="209" w="93" /><ent r="3" t="281" w="410" /><ent r="3" t="281" w="508" /><ent r="3" t="310" w="180" /><ent r="4" t="311" w="36" /><ent r="4" t="311" w="140" /><ent r="4" t="311" w="165" /></phr><phr n="transactions"><ent r="3" t="58" w="643" /><ent r="7" t="61" w="868" /><ent r="3" t="173" w="350" /><ent r="3" t="178" w="116" /><ent r="3" t="188" w="353" /><ent r="3" t="196" w="349" /><ent r="3" t="205" w="96" /><ent r="3" t="281" w="430" /></phr></stem><stem n="(audit"><phr n="(audit"><ent r="3" t="56" w="733" /><ent r="3" t="70" w="651" /><ent r="3" t="187" w="32" /></phr></stem><stem n="keep"><phr n="Keep"><ent r="3" t="56" w="742" /><ent r="3" t="58" w="859" /><ent r="3" t="70" w="660" /><ent r="3" t="118" w="162" /><ent r="3" t="166" w="47" /><ent r="3" t="178" w="243" /><ent r="3" t="189" w="40" /><ent r="3" t="192" w="70" /><ent r="3" t="205" w="221" /><ent r="3" t="277" w="103" /></phr><phr n="keeping"><ent r="8" t="64" w="689" /><ent r="3" t="192" w="43" /></phr></stem><stem n="mind"><phr n="mind"><ent r="3" t="56" w="744" /><ent r="3" t="58" w="861" /><ent r="3" t="70" w="662" /><ent r="3" t="118" w="164" /><ent r="3" t="166" w="49" /><ent r="3" t="178" w="245" /><ent r="3" t="189" w="42" /><ent r="3" t="205" w="223" /><ent r="3" t="277" w="105" /></phr></stem><stem n="-in"><phr n="-in"><ent r="4" t="56" w="767" /><ent r="4" t="56" w="767" /><ent r="7" t="64" w="1103" /><ent r="7" t="64" w="1103" /><ent r="7" t="64" w="1110" /><ent r="7" t="64" w="1110" /><ent r="3" t="70" w="105" /><ent r="3" t="70" w="105" /><ent r="4" t="70" w="754" /><ent r="4" t="70" w="754" /><ent r="3" t="86" w="140" /><ent r="3" t="86" w="140" /><ent r="3" t="116" w="32" /><ent r="3" t="116" w="32" /><ent r="3" t="123" w="24" /><ent r="3" t="123" w="24" /><ent r="3" t="171" w="17" /><ent r="3" t="171" w="17" /></phr></stem><stem n="built"><phr n="built"><ent r="4" t="56" w="767" /><ent r="3" t="70" w="105" /><ent r="4" t="70" w="754" /><ent r="3" t="86" w="140" /><ent r="3" t="116" w="32" /><ent r="3" t="123" w="24" /><ent r="3" t="171" w="17" /></phr></stem><stem n="built-in"><phr n="built-in"><ent r="4" t="56" w="767" /><ent r="3" t="70" w="105" /><ent r="4" t="70" w="754" /><ent r="3" t="86" w="140" /><ent r="3" t="116" w="32" /><ent r="3" t="123" w="24" /><ent r="3" t="171" w="17" /></phr></stem><stem n="cite"><phr n="cite"><ent r="4" t="56" w="801" /><ent r="7" t="56" w="970" /><ent r="7" t="56" w="1079" /><ent r="4" t="70" w="731" /><ent r="7" t="70" w="975" /><ent r="7" t="70" w="1095" /></phr></stem><stem n="sampl"><phr n="sample"><ent r="3" t="56" w="831" /><ent r="3" t="56" w="836" /><ent r="3" t="56" w="845" /><ent r="3" t="56" w="860" /><ent r="3" t="70" w="768" /><ent r="3" t="70" w="773" /><ent r="3" t="70" w="782" /><ent r="3" t="70" w="797" /></phr></stem><stem n="auditset"><phr n="AuditSettings"><ent r="3" t="56" w="838" /><ent r="3" t="70" w="775" /><ent r="5" t="249" w="63" /><ent r="4" t="249" w="81" /></phr></stem><stem n="(sample_server_auditsettings.xml)"><phr n="(Sample_Server_AuditSettings.xml)"><ent r="3" t="56" w="840" /></phr></stem><stem n="conveni"><phr n="convenience"><ent r="3" t="56" w="842" /><ent r="3" t="70" w="779" /></phr></stem><stem n="familiar"><phr n="familiarize"><ent r="3" t="56" w="848" /><ent r="3" t="70" w="785" /></phr></stem><stem n="yourself"><phr n="yourself"><ent r="3" t="56" w="849" /><ent r="3" t="70" w="786" /><ent r="3" t="110" w="50" /></phr></stem><stem n="(default)"><phr n="(default)"><ent r="3" t="56" w="882" /><ent r="3" t="70" w="819" /></phr></stem><stem n="syntax"><phr n="syntax"><ent r="4" t="56" w="911" /><ent r="4" t="56" w="1013" /><ent r="4" t="56" w="1122" /><ent r="4" t="56" w="1207" /><ent r="4" t="70" w="852" /><ent r="4" t="70" w="907" /><ent r="4" t="70" w="1018" /><ent r="4" t="70" w="1138" /><ent r="4" t="70" w="1225" /><ent r="3" t="141" w="54" /><ent r="3" t="147" w="51" /><ent r="3" t="154" w="66" /></phr></stem><stem n="sqlcmcmd"><phr n="SQLcmCmd"><ent r="5" t="56" w="913" /><ent r="5" t="56" w="1015" /><ent r="5" t="56" w="1124" /><ent r="5" t="56" w="1209" /><ent r="5" t="70" w="854" /><ent r="5" t="70" w="909" /><ent r="5" t="70" w="1020" /><ent r="5" t="70" w="1140" /><ent r="5" t="70" w="1227" /><ent r="4" t="141" w="56" /><ent r="4" t="147" w="53" /><ent r="4" t="147" w="89" /><ent r="5" t="153" w="186" /><ent r="4" t="154" w="68" /><ent r="4" t="154" w="101" /></phr></stem><stem n="[-host"><phr n="[-host"><ent r="5" t="56" w="914" /><ent r="5" t="56" w="1016" /><ent r="5" t="56" w="1125" /><ent r="5" t="56" w="1210" /><ent r="5" t="70" w="855" /><ent r="5" t="70" w="910" /><ent r="5" t="70" w="1021" /><ent r="5" t="70" w="1141" /><ent r="5" t="70" w="1228" /><ent r="4" t="141" w="57" /><ent r="4" t="147" w="54" /><ent r="4" t="154" w="69" /></phr></stem><stem n="collectionserv"><phr n="CollectionServer"><ent r="5" t="56" w="915" /><ent r="5" t="56" w="1017" /><ent r="5" t="56" w="1126" /><ent r="5" t="56" w="1211" /><ent r="5" t="70" w="856" /><ent r="5" t="70" w="911" /><ent r="5" t="70" w="1022" /><ent r="5" t="70" w="1142" /><ent r="5" t="70" w="1229" /><ent r="4" t="141" w="58" /><ent r="4" t="147" w="55" /><ent r="4" t="154" w="70" /></phr></stem><stem n="]"><phr n="]"><ent r="5" t="56" w="916" /><ent r="5" t="56" w="918" /><ent r="5" t="56" w="1018" /><ent r="5" t="56" w="1020" /><ent r="5" t="56" w="1127" /><ent r="5" t="56" w="1129" /><ent r="5" t="56" w="1212" /><ent r="5" t="56" w="1214" /><ent r="5" t="70" w="857" /><ent r="5" t="70" w="859" /><ent r="5" t="70" w="912" /><ent r="5" t="70" w="914" /><ent r="5" t="70" w="1023" /><ent r="5" t="70" w="1025" /><ent r="5" t="70" w="1143" /><ent r="5" t="70" w="1145" /><ent r="5" t="70" w="1230" /><ent r="5" t="70" w="1232" /><ent r="4" t="141" w="59" /><ent r="4" t="141" w="61" /><ent r="4" t="141" w="68" /><ent r="4" t="141" w="77" /><ent r="4" t="147" w="56" /><ent r="4" t="147" w="58" /><ent r="4" t="154" w="71" /><ent r="4" t="154" w="73" /></phr></stem><stem n="[-port"><phr n="[-port"><ent r="5" t="56" w="916" /><ent r="5" t="56" w="1018" /><ent r="5" t="56" w="1127" /><ent r="5" t="56" w="1212" /><ent r="5" t="70" w="857" /><ent r="5" t="70" w="912" /><ent r="5" t="70" w="1023" /><ent r="5" t="70" w="1143" /><ent r="5" t="70" w="1230" /><ent r="4" t="141" w="59" /><ent r="4" t="147" w="56" /><ent r="4" t="154" w="71" /></phr></stem><stem n="_server_regulation_guideline.xml"><phr n="_Server_Regulation_Guideline.xml"><ent r="8" t="56" w="950" /><ent r="8" t="56" w="1058" /></phr></stem><stem n="-config"><phr n="-config"><ent r="5" t="56" w="1022" /><ent r="5" t="56" w="1022" /><ent r="5" t="56" w="1131" /><ent r="5" t="56" w="1131" /><ent r="5" t="56" w="1216" /><ent r="5" t="56" w="1216" /><ent r="5" t="70" w="1028" /><ent r="5" t="70" w="1028" /><ent r="5" t="70" w="1148" /><ent r="5" t="70" w="1148" /><ent r="5" t="70" w="1235" /><ent r="5" t="70" w="1235" /></phr></stem><stem n="config"><phr n="config"><ent r="5" t="56" w="1022" /><ent r="5" t="56" w="1131" /><ent r="5" t="56" w="1216" /><ent r="5" t="70" w="1028" /><ent r="5" t="70" w="1148" /><ent r="5" t="70" w="1235" /></phr></stem><stem n="&quot;ferpa"><phr n="&quot;FERPA"><ent r="5" t="56" w="1023" /><ent r="5" t="70" w="1029" /></phr></stem><stem n="&quot;sox"><phr n="&quot;SOX"><ent r="5" t="56" w="1132" /><ent r="5" t="70" w="1149" /></phr></stem><stem n="determin"><phr n="Determine"><ent r="4" t="56" w="1150" /><ent r="7" t="57" w="735" /><ent r="7" t="57" w="741" /><ent r="7" t="57" w="781" /><ent r="7" t="57" w="800" /><ent r="7" t="57" w="828" /><ent r="7" t="57" w="841" /><ent r="7" t="64" w="2371" /><ent r="4" t="70" w="1167" /><ent r="3" t="73" w="13" /><ent r="7" t="92" w="239" /><ent r="3" t="114" w="60" /><ent r="3" t="118" w="45" /><ent r="3" t="124" w="53" /><ent r="3" t="164" w="84" /><ent r="3" t="164" w="211" /><ent r="5" t="165" w="108" /><ent r="3" t="243" w="637" /><ent r="3" t="245" w="247" /><ent r="3" t="282" w="1005" /><ent r="7" t="307" w="78" /><ent r="7" t="308" w="94" /><ent r="3" t="321" w="29" /><ent r="3" t="321" w="82" /></phr><phr n="determination"><ent r="7" t="64" w="322" /></phr><phr n="determinations"><ent r="7" t="64" w="1070" /></phr><phr n="determined"><ent r="7" t="64" w="1362" /></phr><phr n="Determining"><ent r="7" t="64" w="1861" /></phr><phr n="determines"><ent r="3" t="88" w="75" /><ent r="3" t="163" w="35" /></phr></stem><stem n="&quot;export"><phr n="&quot;exported"><ent r="5" t="56" w="1217" /><ent r="5" t="70" w="1236" /></phr></stem><stem n="corpor"><phr n="corporate"><ent r="3" t="57" w="41" /><ent r="3" t="92" w="86" /><ent r="3" t="94" w="109" /><ent r="3" t="99" w="111" /><ent r="3" t="102" w="112" /><ent r="3" t="279" w="238" /></phr></stem><stem n="privaci"><phr n="privacy"><ent r="3" t="57" w="44" /><ent r="7" t="64" w="255" /><ent r="7" t="64" w="1201" /><ent r="7" t="64" w="1395" /><ent r="3" t="92" w="89" /></phr></stem><stem n="demonstr"><phr n="demonstrate"><ent r="3" t="57" w="60" /><ent r="3" t="92" w="125" /><ent r="3" t="111" w="70" /></phr><phr n="demonstrates"><ent r="3" t="313" w="87" /></phr></stem><stem n=":prepar"><phr n=":preparation"><ent r="100" t="57" w="82" /><ent r="100" t="92" w="35" /></phr></stem><stem n=":requir"><phr n=":requirements"><ent r="100" t="57" w="86" /></phr></stem><stem n="rememb"><phr n="Remember"><ent r="7" t="57" w="281" /><ent r="7" t="57" w="366" /><ent r="4" t="315" w="91" /></phr></stem><stem n="exactli"><phr n="exactly"><ent r="7" t="57" w="313" /><ent r="7" t="57" w="398" /><ent r="3" t="209" w="84" /></phr></stem><stem n="exclud"><phr n="excluded"><ent r="6" t="57" w="410" /><ent r="100" t="78" w="23" /><ent r="3" t="78" w="103" /><ent r="3" t="239" w="477" /><ent r="3" t="244" w="257" /></phr><phr n="exclude"><ent r="7" t="57" w="419" /><ent r="7" t="57" w="598" /><ent r="4" t="72" w="96" /><ent r="6" t="73" w="128" /><ent r="3" t="74" w="17" /><ent r="4" t="74" w="101" /><ent r="4" t="74" w="136" /><ent r="3" t="78" w="46" /><ent r="4" t="78" w="182" /><ent r="4" t="78" w="217" /><ent r="3" t="83" w="186" /><ent r="7" t="85" w="257" /><ent r="8" t="93" w="230" /><ent r="8" t="93" w="266" /><ent r="8" t="93" w="305" /><ent r="3" t="244" w="460" /></phr><phr n="Excludes"><ent r="1000" t="78" w="9" /><ent r="102" t="78" w="17" /><ent r="3" t="78" w="37" /><ent r="3" t="78" w="135" /></phr><phr n="excluding"><ent r="3" t="80" w="38" /><ent r="7" t="85" w="322" /></phr></stem><stem n="filter"><phr n="filters"><ent r="68" t="57" w="426" /><ent r="82" t="57" w="567" /><ent r="7" t="57" w="583" /><ent r="7" t="57" w="589" /><ent r="68" t="57" w="606" /><ent r="7" t="57" w="678" /><ent r="68" t="57" w="690" /><ent r="7" t="62" w="417" /><ent r="1000" t="72" w="3" /><ent r="102" t="72" w="6" /><ent r="100" t="72" w="12" /><ent r="3" t="72" w="19" /><ent r="3" t="72" w="40" /><ent r="3" t="72" w="57" /><ent r="3" t="72" w="72" /><ent r="3" t="72" w="88" /><ent r="1000" t="73" w="3" /><ent r="102" t="73" w="8" /><ent r="3" t="73" w="12" /><ent r="3" t="73" w="33" /><ent r="3" t="73" w="67" /><ent r="3" t="74" w="36" /><ent r="5" t="74" w="68" /><ent r="100" t="75" w="22" /><ent r="100" t="75" w="26" /><ent r="3" t="75" w="54" /><ent r="5" t="75" w="133" /><ent r="1000" t="76" w="4" /><ent r="102" t="76" w="9" /><ent r="3" t="76" w="41" /><ent r="3" t="76" w="52" /><ent r="3" t="76" w="66" /><ent r="3" t="76" w="84" /><ent r="3" t="76" w="98" /><ent r="3" t="76" w="112" /><ent r="5" t="76" w="118" /><ent r="5" t="76" w="130" /><ent r="5" t="76" w="136" /><ent r="4" t="76" w="162" /><ent r="1000" t="77" w="4" /><ent r="102" t="77" w="9" /><ent r="3" t="77" w="17" /><ent r="3" t="77" w="30" /><ent r="3" t="77" w="43" /><ent r="3" t="77" w="62" /><ent r="5" t="77" w="68" /><ent r="5" t="77" w="80" /><ent r="4" t="77" w="101" /><ent r="100" t="78" w="20" /><ent r="3" t="78" w="33" /><ent r="64" t="78" w="84" /><ent r="5" t="78" w="141" /><ent r="100" t="79" w="12" /><ent r="5" t="79" w="52" /><ent r="5" t="79" w="65" /><ent r="100" t="80" w="12" /><ent r="5" t="80" w="89" /><ent r="5" t="80" w="102" /><ent r="64" t="83" w="183" /><ent r="7" t="85" w="238" /><ent r="7" t="85" w="240" /><ent r="7" t="85" w="255" /><ent r="68" t="85" w="283" /><ent r="7" t="85" w="290" /><ent r="7" t="85" w="293" /><ent r="3" t="90" w="125" /><ent r="3" t="90" w="167" /><ent r="3" t="90" w="211" /><ent r="4" t="96" w="303" /><ent r="5" t="120" w="96" /><ent r="3" t="157" w="320" /><ent r="3" t="168" w="241" /><ent r="3" t="170" w="180" /><ent r="65" t="174" w="601" /><ent r="1000" t="175" w="7" /><ent r="92" t="175" w="16" /><ent r="3" t="181" w="70" /><ent r="1000" t="190" w="9" /><ent r="92" t="190" w="18" /><ent r="3" t="213" w="149" /><ent r="1000" t="226" w="7" /><ent r="92" t="226" w="17" /><ent r="3" t="238" w="124" /><ent r="1000" t="239" w="2" /><ent r="102" t="239" w="6" /><ent r="3" t="239" w="37" /><ent r="3" t="239" w="288" /><ent r="3" t="239" w="295" /><ent r="3" t="239" w="308" /><ent r="3" t="239" w="313" /><ent r="3" t="239" w="320" /><ent r="3" t="239" w="340" /><ent r="3" t="239" w="424" /><ent r="3" t="244" w="264" /><ent r="3" t="244" w="271" /><ent r="3" t="244" w="292" /><ent r="3" t="244" w="444" /><ent r="3" t="244" w="449" /><ent r="3" t="244" w="458" /><ent r="3" t="245" w="951" /><ent r="3" t="245" w="958" /><ent r="3" t="245" w="981" /><ent r="1000" t="262" w="7" /><ent r="92" t="262" w="17" /><ent r="3" t="294" w="133" /></phr><phr n="Filtering"><ent r="92" t="58" w="489" /><ent r="100" t="72" w="8" /><ent r="100" t="75" w="17" /><ent r="3" t="79" w="18" /><ent r="3" t="79" w="32" /><ent r="3" t="80" w="18" /><ent r="3" t="80" w="33" /><ent r="3" t="231" w="111" /><ent r="3" t="239" w="348" /><ent r="1000" t="254" w="2" /><ent r="102" t="254" w="7" /><ent r="3" t="254" w="18" /><ent r="3" t="254" w="20" /><ent r="3" t="254" w="34" /><ent r="3" t="254" w="87" /><ent r="3" t="254" w="123" /><ent r="3" t="254" w="154" /><ent r="3" t="267" w="158" /></phr><phr n="filter"><ent r="3" t="58" w="703" /><ent r="3" t="63" w="26" /><ent r="3" t="72" w="43" /><ent r="6" t="73" w="126" /><ent r="1000" t="74" w="4" /><ent r="102" t="74" w="9" /><ent r="3" t="74" w="13" /><ent r="3" t="74" w="62" /><ent r="5" t="74" w="81" /><ent r="4" t="74" w="134" /><ent r="4" t="74" w="156" /><ent r="4" t="74" w="163" /><ent r="4" t="74" w="190" /><ent r="4" t="74" w="205" /><ent r="4" t="74" w="220" /><ent r="1000" t="75" w="4" /><ent r="102" t="75" w="12" /><ent r="3" t="75" w="35" /><ent r="3" t="75" w="40" /><ent r="3" t="75" w="45" /><ent r="3" t="75" w="70" /><ent r="3" t="75" w="75" /><ent r="3" t="75" w="89" /><ent r="3" t="75" w="99" /><ent r="3" t="75" w="104" /><ent r="3" t="75" w="112" /><ent r="3" t="75" w="118" /><ent r="3" t="75" w="124" /><ent r="4" t="75" w="145" /><ent r="4" t="75" w="149" /><ent r="5" t="75" w="163" /><ent r="4" t="75" w="187" /><ent r="4" t="75" w="199" /><ent r="4" t="75" w="208" /><ent r="4" t="75" w="222" /><ent r="3" t="76" w="13" /><ent r="4" t="77" w="86" /><ent r="1000" t="78" w="8" /><ent r="102" t="78" w="16" /><ent r="3" t="78" w="91" /><ent r="3" t="78" w="134" /><ent r="4" t="78" w="152" /><ent r="4" t="78" w="215" /><ent r="4" t="78" w="237" /><ent r="4" t="78" w="244" /><ent r="4" t="78" w="271" /><ent r="1000" t="79" w="4" /><ent r="102" t="79" w="9" /><ent r="3" t="79" w="38" /><ent r="3" t="79" w="46" /><ent r="4" t="79" w="70" /><ent r="5" t="79" w="80" /><ent r="1000" t="80" w="4" /><ent r="102" t="80" w="9" /><ent r="3" t="80" w="50" /><ent r="3" t="80" w="71" /><ent r="3" t="80" w="77" /><ent r="3" t="80" w="83" /><ent r="4" t="80" w="107" /><ent r="5" t="80" w="117" /><ent r="7" t="85" w="311" /><ent r="7" t="85" w="320" /><ent r="4" t="90" w="102" /><ent r="3" t="90" w="144" /><ent r="4" t="90" w="262" /><ent r="4" t="90" w="357" /><ent r="3" t="157" w="325" /><ent r="3" t="168" w="246" /><ent r="3" t="170" w="185" /><ent r="3" t="173" w="84" /><ent r="4" t="173" w="143" /><ent r="3" t="173" w="167" /><ent r="3" t="173" w="181" /><ent r="7" t="173" w="196" /><ent r="3" t="178" w="176" /><ent r="3" t="178" w="268" /><ent r="3" t="181" w="75" /><ent r="3" t="188" w="87" /><ent r="4" t="188" w="146" /><ent r="3" t="188" w="170" /><ent r="3" t="188" w="184" /><ent r="7" t="188" w="199" /><ent r="3" t="199" w="128" /><ent r="4" t="199" w="187" /><ent r="3" t="199" w="208" /><ent r="3" t="199" w="222" /><ent r="7" t="199" w="237" /><ent r="3" t="205" w="156" /><ent r="3" t="205" w="246" /><ent r="3" t="212" w="46" /><ent r="3" t="213" w="154" /><ent r="1000" t="231" w="3" /><ent r="1000" t="231" w="7" /><ent r="102" t="231" w="11" /><ent r="92" t="231" w="16" /><ent r="3" t="231" w="20" /><ent r="3" t="231" w="49" /><ent r="3" t="231" w="58" /><ent r="3" t="231" w="73" /><ent r="3" t="231" w="85" /><ent r="3" t="231" w="99" /><ent r="3" t="231" w="135" /><ent r="3" t="231" w="145" /><ent r="1000" t="232" w="3" /><ent r="102" t="232" w="13" /><ent r="3" t="232" w="41" /><ent r="3" t="232" w="85" /><ent r="3" t="232" w="90" /><ent r="3" t="232" w="114" /><ent r="3" t="232" w="125" /><ent r="3" t="232" w="131" /><ent r="3" t="232" w="271" /><ent r="3" t="232" w="282" /><ent r="3" t="232" w="295" /><ent r="3" t="232" w="302" /><ent r="3" t="232" w="321" /><ent r="3" t="232" w="330" /><ent r="3" t="232" w="333" /><ent r="1000" t="233" w="3" /><ent r="102" t="233" w="12" /><ent r="3" t="233" w="42" /><ent r="3" t="233" w="57" /><ent r="3" t="233" w="79" /><ent r="3" t="233" w="87" /><ent r="3" t="233" w="111" /><ent r="3" t="233" w="123" /><ent r="3" t="233" w="127" /><ent r="3" t="233" w="144" /><ent r="3" t="233" w="153" /><ent r="3" t="233" w="156" /><ent r="1000" t="234" w="3" /><ent r="102" t="234" w="12" /><ent r="3" t="234" w="35" /><ent r="3" t="234" w="49" /><ent r="3" t="234" w="70" /><ent r="3" t="234" w="90" /><ent r="3" t="234" w="102" /><ent r="3" t="234" w="106" /><ent r="3" t="234" w="123" /><ent r="3" t="234" w="132" /><ent r="3" t="234" w="135" /><ent r="3" t="238" w="129" /><ent r="3" t="239" w="14" /><ent r="3" t="239" w="60" /><ent r="4" t="239" w="69" /><ent r="3" t="239" w="82" /><ent r="3" t="239" w="87" /><ent r="3" t="239" w="96" /><ent r="3" t="239" w="101" /><ent r="3" t="239" w="109" /><ent r="3" t="239" w="115" /><ent r="3" t="239" w="126" /><ent r="3" t="239" w="130" /><ent r="3" t="239" w="140" /><ent r="3" t="239" w="151" /><ent r="3" t="239" w="165" /><ent r="3" t="239" w="172" /><ent r="3" t="239" w="178" /><ent r="3" t="239" w="183" /><ent r="3" t="239" w="192" /><ent r="3" t="239" w="196" /><ent r="3" t="239" w="211" /><ent r="4" t="239" w="218" /><ent r="3" t="239" w="245" /><ent r="3" t="239" w="256" /><ent r="3" t="239" w="265" /><ent r="3" t="239" w="283" /><ent r="3" t="239" w="370" /><ent r="3" t="239" w="382" /><ent r="3" t="239" w="387" /><ent r="3" t="239" w="399" /><ent r="3" t="239" w="433" /><ent r="3" t="239" w="442" /><ent r="3" t="239" w="457" /><ent r="3" t="239" w="480" /><ent r="3" t="239" w="491" /><ent r="3" t="239" w="496" /><ent r="3" t="239" w="505" /><ent r="1000" t="267" w="3" /><ent r="1000" t="267" w="7" /><ent r="102" t="267" w="11" /><ent r="92" t="267" w="16" /><ent r="3" t="267" w="25" /><ent r="3" t="267" w="28" /><ent r="3" t="267" w="47" /><ent r="3" t="267" w="52" /><ent r="3" t="267" w="74" /><ent r="3" t="267" w="82" /><ent r="3" t="267" w="89" /><ent r="3" t="267" w="96" /><ent r="3" t="267" w="105" /><ent r="3" t="267" w="120" /><ent r="3" t="267" w="132" /><ent r="3" t="267" w="146" /><ent r="3" t="267" w="182" /><ent r="3" t="267" w="192" /><ent r="1000" t="268" w="3" /><ent r="102" t="268" w="12" /><ent r="3" t="268" w="42" /><ent r="3" t="268" w="57" /><ent r="3" t="268" w="79" /><ent r="3" t="268" w="87" /><ent r="3" t="268" w="111" /><ent r="3" t="268" w="123" /><ent r="3" t="268" w="127" /><ent r="3" t="268" w="145" /><ent r="3" t="268" w="154" /><ent r="3" t="268" w="157" /><ent r="1000" t="269" w="3" /><ent r="102" t="269" w="12" /><ent r="3" t="269" w="35" /><ent r="3" t="269" w="49" /><ent r="3" t="269" w="70" /><ent r="3" t="269" w="90" /><ent r="3" t="269" w="102" /><ent r="3" t="269" w="106" /><ent r="3" t="269" w="124" /><ent r="3" t="269" w="133" /><ent r="3" t="269" w="136" /><ent r="1000" t="270" w="3" /><ent r="102" t="270" w="12" /><ent r="3" t="270" w="39" /><ent r="3" t="270" w="83" /><ent r="3" t="270" w="88" /><ent r="3" t="270" w="112" /><ent r="3" t="270" w="124" /><ent r="3" t="270" w="130" /><ent r="3" t="270" w="270" /><ent r="3" t="270" w="281" /><ent r="3" t="270" w="294" /><ent r="3" t="270" w="301" /><ent r="3" t="270" w="320" /><ent r="3" t="270" w="329" /><ent r="3" t="270" w="332" /><ent r="3" t="278" w="131" /><ent r="4" t="278" w="190" /><ent r="3" t="278" w="211" /><ent r="3" t="278" w="225" /><ent r="7" t="278" w="240" /><ent r="1000" t="287" w="3" /><ent r="102" t="287" w="9" /><ent r="3" t="287" w="29" /><ent r="3" t="287" w="39" /><ent r="3" t="287" w="64" /><ent r="3" t="287" w="79" /><ent r="3" t="287" w="114" /><ent r="3" t="287" w="125" /><ent r="3" t="287" w="168" /><ent r="3" t="287" w="178" /><ent r="3" t="287" w="377" /><ent r="3" t="294" w="138" /></phr><phr n="filtered"><ent r="3" t="58" w="866" /><ent r="3" t="178" w="250" /><ent r="3" t="205" w="228" /><ent r="3" t="232" w="37" /><ent r="3" t="244" w="745" /><ent r="3" t="270" w="35" /></phr></stem></index>